moduleana/__init__.py
moduleana/module.py
moduleana-0.3.dist-info/METADATA
moduleana-0.3.dist-info/WHEEL
moduleana-0.3.dist-info/top_level.txt
moduleana-0.3.dist-info/RECORD
