Metadata-Version: 2.1
Name: moduleana
Version: 0.3
Requires-Dist: numpy
Requires-Dist: matplotlib
